tgml/__init__.py
tgml/data.py
tgml/dataloaders.py
tgml/featurizer.py
tgml/metrics.py
tgml/utils.py
tgml/extras/__init__.py
tgml/extras/utilities.py
tgml-0.1.12.dist-info/LICENSE
tgml-0.1.12.dist-info/METADATA
tgml-0.1.12.dist-info/WHEEL
tgml-0.1.12.dist-info/top_level.txt
tgml-0.1.12.dist-info/RECORD
