Metadata-Version: 2.1
Name: tgml
Version: 0.1.12
Summary: ML Workbench
Home-page: https://github.com/TigerGraph-DevLabs/tgml
Author: Bill Shi
Author-email: bill.shi@tigergraph.com
License: UNKNOWN
Project-URL: Bug Tracker, https://github.com/TigerGraph-DevLabs/tgml/issues
Platform: UNKNOWN
Classifier: Development Status :: 3 - Alpha
Classifier: Intended Audience :: Developers
Classifier: Programming Language :: Python :: 3
Classifier: License :: OSI Approved :: MIT License
Classifier: Operating System :: OS Independent
Requires-Python: >=3.6
License-File: LICENSE
Requires-Dist: requests
Requires-Dist: python-dotenv
Requires-Dist: pandas
Requires-Dist: numpy
Requires-Dist: torch
Requires-Dist: boto3
Requires-Dist: google-cloud-storage
Provides-Extra: dgl
Requires-Dist: dgl ; extra == 'dgl'
Provides-Extra: pyg
Requires-Dist: torch-sparse ; extra == 'pyg'
Requires-Dist: torch-scatter ; extra == 'pyg'
Requires-Dist: torch-geometric ; extra == 'pyg'
